module/__init__.py
module/fuzzy_operations.py
fuzzy_pratish-0.4.dist-info/LICENSE.txt
fuzzy_pratish-0.4.dist-info/METADATA
fuzzy_pratish-0.4.dist-info/WHEEL
fuzzy_pratish-0.4.dist-info/top_level.txt
fuzzy_pratish-0.4.dist-info/RECORD
